ektis/__init__.py
ektis/client.py
ektis/embed.py
ektis/logging.py
ektis/moraapi.py
ektis/send.py
ektis-0.0.3.dist-info/METADATA
ektis-0.0.3.dist-info/WHEEL
ektis-0.0.3.dist-info/top_level.txt
ektis-0.0.3.dist-info/RECORD
